ocr_poetry_pkg/__init__.py
ocr_poetry_pkg/cli.py
ocr_poetry_pkg/layout.py
ocr_poetry_pkg/pdf2img.py
ocr_poetry_pkg-0.1.0.dist-info/METADATA
ocr_poetry_pkg-0.1.0.dist-info/WHEEL
ocr_poetry_pkg-0.1.0.dist-info/entry_points.txt
ocr_poetry_pkg-0.1.0.dist-info/RECORD
