Metadata-Version: 2.1
Name: ocr-poetry-pkg
Version: 0.1.0
Summary:  OCR CLI for Arabic images using unsloth/surya
Author: alka gupta
Author-email: alka.gupta@ksolves.com
Requires-Python: >=3.12,<4.0
Classifier: Programming Language :: Python :: 3
Classifier: Programming Language :: Python :: 3.12
Requires-Dist: click (>=8.3.0,<9.0.0)
Requires-Dist: pillow (>=12.0.0,<13.0.0)
